pistachio/__init__.py
pistachio-0.7.0.dist-info/LICENSE
pistachio-0.7.0.dist-info/WHEEL
pistachio-0.7.0.dist-info/METADATA
pistachio-0.7.0.dist-info/RECORD
