Metadata-Version: 2.1
Name: pistachio
Version: 0.7.0
Summary: Pistachio aims to simplify reoccurring tasks when working with the file system.
Author-email: Matthew Akino-Wittering <matthew.akinowittering@outlook.com>
Classifier: License :: OSI Approved :: MIT License
Project-URL: Home, https://github.com/mjakinowittering/pistachio
